{
  "locations": {
    "CYS20_F01C01": 15,
    "DSM18_F01C01": 15,
    "DSM18_F01C02": 15,
    "DSM18_F01C03": 15,
    "DSM18_F01C04": 15,
    "DSM18_F01C05": 15,
    "DSM45_F01C01": 15,
    "DSM45_F01C02": 15,
    "DSM45_F01C03": 15,
    "DSM45_F01C04": 15,
    "DSM45_F01C05": 15,
    "PHX16_F01C01": 15,
    "SAT16_F01C01": 15,
    "SAT82_F01C01": 15,
    "JKT09_F01C02": 15,
    "JKT11_F01C02": 15,
    "AVC11_F01C01": 14,
    "CMH02_F01C01": 14,
    "CMH18_F01C01": 14,
    "CMH18_F01C02": 14,
    "CMH18_F01C03": 14,
    "CMH18_F01C04": 14,
    "CMH18_F01C05": 14,
    "CMH47_F01C01": 14,
    "CMH47_F01C02": 14,
    "CMH47_F01C03": 14,
    "CMH47_F01C04": 14,
    "CMH47_F01C05": 14,
    "CYS20_F01C02": 14,
    "CYS20_F01C03": 14,
    "CYS20_F01C04": 14,
    "CYS20_F01C05": 14,
    "EAT06_F01C03": 14,
    "EAT06_F02C01": 14,
    "EKI01_F01C01": 14,
    "EKI01_F01C05": 14,
    "EKI02_F01C01": 14,
    "EKI02_F01C05": 14,
    "LPO01_F01C01": 14,
    "LPO01_F01C05": 14,
    "LPO02_F01C01": 14,
    "LPO02_F01C05": 14,
    "MKE07_F01C01": 14,
    "MKE08_F01C01": 14,
    "MKE08_F01C05": 14,
    "MKE09_F01C01": 14,
    "PHX16_F01C02": 14,
    "PHX16_F01C03": 14,
    "PHX16_F01C04": 14,
    "PHX16_F01C05": 14
  },
  "materials": {
    "C00000560-001": 1248,
    "C00000553-001": 1223,
    "C00000561-001": 1222,
    "C00000579-001": 1180,
    "C00000559-001": 1118,
    "C00000578-001": 1109,
    "C00000564-001": 989,
    "C00000587-001": 900,
    "C00000562-001": 859,
    "C00000576-001": 793,
    "C00000575-001": 666,
    "C00000583-001": 478,
    "C00000588-001": 415,
    "C00000586-001": 346,
    "C00024166-001": 258,
    "C00001872-001": 154,
    "C00000563-001": 150,
    "C00000584-001": 24,
    "C00034775-001": 15,
    "C00000582-001": 1
  },
  "categories": {
    "UPS": 1248,
    "MVSXRM": 1223,
    "LVS": 1222,
    "EPMS": 1180,
    "ATS": 1118,
    "BAS": 1109,
    "GEN": 989,
    "BUS": 900,
    "MVS": 859,
    "AHU": 793,
    "HAC": 666,
    "ACC": 478,
    "CRAH": 415,
    "CDU": 346,
    "AHF": 258,
    "TCP": 154,
    "PDU": 150,
    "CT": 24,
    "EHOUSE": 15,
    "WCC": 1
  },
  "suppliers": {
    "210_AMER": 1646,
    "530_AMER": 1572,
    "540_AMER": 737,
    "540_EMEA": 654,
    "9999_AMER": 640,
    "530_EMEA": 551,
    "10_AMER": 520,
    "70_AMER": 497,
    "210_EMEA": 453,
    "560_AMER": 384,
    "40_EMEA": 353,
    "320_AMER": 338,
    "130_AMER": 325,
    "170_AMER": 310,
    "530_APAC": 282,
    "260_EMEA": 274,
    "600_AMER": 271,
    "9999_EMEA": 254,
    "10_EMEA": 215,
    "10_APAC": 165,
    "1690_AMER": 151,
    "320_EMEA": 144,
    "540_APAC": 135,
    "1670_AMER": 134,
    "570_AMER": 125,
    "320_APAC": 124,
    "310_AMER": 111,
    "570_EMEA": 94,
    "200_EMEA": 91,
    "130_EMEA": 85,
    "260_AMER": 84,
    "390_AMER": 82,
    "625_AMER": 82,
    "110_AMER": 77,
    "210_APAC": 74,
    "290_AMER": 73,
    "405_EMEA": 65,
    "290_EMEA": 59,
    "70_EMEA": 58,
    "1670_EMEA": 53,
    "190_AMER": 51,
    "178_AMER": 50,
    "625_EMEA": 47,
    "40_AMER": 46,
    "170_EMEA": 45,
    "1710_EMEA": 41,
    "113_AMER": 40,
    "560_EMEA": 38,
    "600_EMEA": 36,
    "520_EMEA": 35
  }
}